{
  "metadata": {
    "slug": "vox-larmor-precession",
    "title": "The Spinning Compass Inside Every MRI",
    "topic": "QUANTUM MECHANICS",
    "source": "quantum-mechanics-vol2/chapters/07-spin-and-the-bloch-sphere.md",
    "voice_id": "TyW6NH39JcFb5M3xdIIk",
    "aspect_ratio": "16:9",
    "style_preset": "vox-editorial",
    "color_semantics": "TEAL = the fixed z-component (what the MRI scanner reads); CRIMSON = the precessing azimuthal motion (the frequency the scanner listens for)",
    "note": "Exclusions honored: no Hamiltonian diagonalization, no g-factor/QED aside, no pulse-sequence engineering. Mechanism only: spin in z-field keeps polar angle fixed while azimuth advances at Larmor frequency omega=gamma*B.",
    "total_estimated_duration_seconds": 168.02
  },
  "beats": [
    {
      "beat_id": "B01",
      "t_start": 0.0,
      "estimated_duration_s": 10.0,
      "narration_text": "Every MRI scanner works by listening. Millions of proton spins inside you are circling at the same frequency — and the scanner picks up that exact rotation.",
      "shot": {
        "type": "CARD",
        "source": "own",
        "motion": "hold"
      },
      "card": {
        "kind": "title",
        "copy": "The Spinning Compass Inside Every MRI",
        "sub": "QUANTUM MECHANICS"
      },
      "act": "COLD OPEN",
      "audio_file": "mp3/beat-B01.mp3",
      "actual_duration_s": 9.46
    },
    {
      "beat_id": "B02",
      "t_start": 10.0,
      "estimated_duration_s": 11.0,
      "narration_text": "Drop a proton into a magnetic field pointing up. The proton's spin arrow tilts at some angle — and then, instead of staying still, it starts to circle. Like a tilted top that won't fall.",
      "shot": {
        "type": "GRAPHIC",
        "source": "own",
        "motion": "rotate"
      },
      "act": "COLD OPEN",
      "audio_file": "mp3/beat-B02.mp3",
      "actual_duration_s": 12.02
    },
    {
      "beat_id": "B03",
      "t_start": 21.0,
      "estimated_duration_s": 10.0,
      "narration_text": "The z-component stays exactly fixed the whole time. Only the horizontal part rotates. The spin is on a circle at constant latitude — precessing.",
      "shot": {
        "type": "GRAPHIC",
        "source": "own",
        "motion": "rotate"
      },
      "act": "COLD OPEN",
      "audio_file": "mp3/beat-B03.mp3",
      "actual_duration_s": 9.14
    },
    {
      "beat_id": "B04",
      "t_start": 31.0,
      "estimated_duration_s": 11.0,
      "narration_text": "The Question: the z-component of the spin never changes. Yet the spin is clearly doing something — circling at a constant rate. What fixes that rate, and why does the z-component stay frozen?",
      "shot": {
        "type": "CARD",
        "source": "own",
        "motion": "hold"
      },
      "card": {
        "kind": "question",
        "copy": "Lz is frozen. The azimuth rotates. What sets the rate, and why the split?"
      },
      "act": "THE QUESTION",
      "audio_file": "mp3/beat-B04.mp3",
      "actual_duration_s": 11.96
    },
    {
      "beat_id": "B05",
      "t_start": 42.0,
      "estimated_duration_s": 11.0,
      "narration_text": "Naive picture: the field should push the spin to align — either all the way up, or all the way down. Classical magnets align. Why does the quantum spin just circle instead?",
      "shot": {
        "type": "GRAPHIC",
        "source": "own",
        "motion": "compare"
      },
      "act": "THE PROBLEM",
      "audio_file": "mp3/beat-B05.mp3",
      "actual_duration_s": 10.68
    },
    {
      "beat_id": "B06",
      "t_start": 53.0,
      "estimated_duration_s": 11.0,
      "narration_text": "The mechanism: the field makes each spin eigenstate advance its phase at a different rate. The up-state gains phase at one speed, the down-state at another. Their relative phase is the azimuth on the Bloch sphere — and that relative phase ticks forward at their difference.",
      "shot": {
        "type": "GRAPHIC",
        "source": "own",
        "motion": "rotate"
      },
      "act": "THE MECHANISM",
      "audio_file": "mp3/beat-B06.mp3",
      "actual_duration_s": 16.25
    },
    {
      "beat_id": "B07",
      "t_start": 64.0,
      "estimated_duration_s": 11.0,
      "narration_text": "The rate of that advance is the Larmor frequency: omega equals gamma times B. Gamma is the gyromagnetic ratio — it depends only on the particle. B is the field strength. Double the field, double the frequency.",
      "shot": {
        "type": "GRAPHIC",
        "source": "own",
        "motion": "compare"
      },
      "act": "THE MECHANISM",
      "audio_file": "mp3/beat-B07.mp3",
      "actual_duration_s": 14.76
    },
    {
      "beat_id": "B08",
      "t_start": 75.0,
      "estimated_duration_s": 11.0,
      "narration_text": "Why does Lz stay fixed? The phase advance on each eigenstate doesn't change the probability of finding the spin up or down — only the relative phase between them changes. The polar angle is unchanged. Only the azimuth moves.",
      "shot": {
        "type": "GRAPHIC",
        "source": "own",
        "motion": "compare"
      },
      "act": "THE MECHANISM",
      "audio_file": "mp3/beat-B08.mp3",
      "actual_duration_s": 14.52
    },
    {
      "beat_id": "B09",
      "t_start": 86.0,
      "estimated_duration_s": 12.0,
      "narration_text": "In a 1.5 Tesla clinical MRI scanner, protons precess at 63.9 megahertz — 64 million circles per second. At 3 Tesla, the rate doubles to 127.7 megahertz. The scanner broadcasts a radio pulse at exactly that frequency, and the spins answer.",
      "shot": {
        "type": "STILL",
        "source": "ai",
        "motion": "kenburns",
        "remotion": {
          "pattern": "SlateCard",
          "provenance": "proven-core/SlateCard",
          "version": "1",
          "props": {
            "headline": "In a 1.5 Tesla clinical MRI scanner, protons precess at 63.9…",
            "eyebrow": "THE IMPLICATION",
            "topic": "QUANTUM MECHANICS"
          },
          "rendered": {
            "out": "media/B09.mp4",
            "at": ""
          }
        }
      },
      "scene_description": "Interior of a clinical MRI scanner bore, circular magnets surrounding a patient table, showing the scale and field geometry",
      "act": "THE IMPLICATION",
      "audio_file": "mp3/beat-B09.mp3",
      "actual_duration_s": 19.41
    },
    {
      "beat_id": "B10",
      "t_start": 98.0,
      "estimated_duration_s": 12.0,
      "narration_text": "A physicist sets up a proton with spin tilted at 60 degrees from the z-axis, inside a 1.5 Tesla field. She calculates: z-component is hbar times cosine 60, which is hbar over 2. That value never changes. Azimuth advances at 63.9 MHz. She measures: the probability of spin-up stays constant, the transverse signal oscillates at exactly 63.9 MHz.",
      "shot": {
        "type": "GRAPHIC",
        "source": "own",
        "motion": "compare"
      },
      "act": "THE EXAMPLE",
      "example_note": "illustrative — numbers from the chapter's worked example at 1.5 T",
      "audio_file": "mp3/beat-B10.mp3",
      "actual_duration_s": 27.59
    },
    {
      "beat_id": "B11",
      "t_start": 110.0,
      "estimated_duration_s": 10.0,
      "narration_text": "Why does a proton spin circle in a magnetic field without ever aligning? Because the field advances the relative phase of the up and down eigenstates — moving the azimuth — while leaving the amplitudes, and therefore the z-projection, exactly unchanged.",
      "shot": {
        "type": "CARD",
        "source": "own",
        "motion": "hold"
      },
      "card": {
        "kind": "endcard",
        "copy": "omega = gamma * B. The z-component is frozen. The azimuth circles.",
        "kicker": "QUANTUM MECHANICS"
      },
      "act": "RECAP",
      "audio_file": "mp3/beat-B11.mp3",
      "actual_duration_s": 16.254
    },
    {
      "beat_id": "B12",
      "act": "OUTRO",
      "type": "GRAPHIC",
      "name": "OutroSeries",
      "narration_text": "Part of the Quantum Mechanics: Formalism and the Three-Dimensional Atom series.",
      "shot": {
        "type": "GRAPHIC",
        "source": "remotion",
        "motion": "fade",
        "scene_type": "outro-series",
        "remotion": {
          "pattern": "OutroSeries",
          "provenance": "proven-core/OutroSeries",
          "version": "1",
          "props": {
            "seriesTitle": "Quantum Mechanics: Formalism and the Three-Dimensional Atom",
            "tagline": "",
            "githubSlug": "quantum-mechanics-vol2"
          }
        }
      },
      "estimated_duration_s": 6,
      "audio_file": "mp3/beat-B12.mp3",
      "actual_duration_s": 4.44
    },
    {
      "beat_id": "B13",
      "act": "OUTRO",
      "type": "GRAPHIC",
      "name": "OutroCTA",
      "narration_text": "Like and subscribe for more.",
      "shot": {
        "type": "GRAPHIC",
        "source": "remotion",
        "motion": "fade",
        "scene_type": "outro-cta",
        "remotion": {
          "pattern": "OutroCTA",
          "provenance": "proven-core/OutroCTA",
          "version": "1",
          "props": {
            "authorName": "Nik Bear Brown",
            "handle": "@NikBearBrown",
            "ctaText": "Like and subscribe for more."
          }
        }
      },
      "estimated_duration_s": 5,
      "audio_file": "mp3/beat-B13.mp3",
      "actual_duration_s": 1.49
    }
  ]
}